MasterPB_STT/__init__.py
MasterPB_STT-0.1.dist-info/METADATA
MasterPB_STT-0.1.dist-info/WHEEL
MasterPB_STT-0.1.dist-info/top_level.txt
MasterPB_STT-0.1.dist-info/RECORD
