Metadata-Version: 2.1
Name: MasterPB-STT
Version: 0.1
Summary: this is speech to text real time package crated by MasterPB best STT
Author: MasterPB
Author-email: example@gmail.com
